H_MCRLLM/__init__.py
H_MCRLLM/h_mcrllm.py
H_MCRLLM/half_mcr.py
H_MCRLLM/mcrllm.py
H_MCRLLM/pointselector.py
H_MCRLLM/preprocessing.py
H_MCRLLM/select_with_PCA.py
H_MCRLLM/use_full_MCR.py
H_MCRLLM/use_half_MCR.py
H_MCRLLM-0.0.24.dist-info/METADATA
H_MCRLLM-0.0.24.dist-info/WHEEL
H_MCRLLM-0.0.24.dist-info/top_level.txt
H_MCRLLM-0.0.24.dist-info/RECORD
