Metadata-Version: 2.1
Name: H-MCRLLM
Version: 0.0.24
Summary: H MCRLLM: Hierarchical Multivariate Curve Resolution by Log-Likelihood Maximization
Home-page: UNKNOWN
Author: Ryan Gosselin
Author-email: ryan.gosselin@usherbrooke.ca
License: UNKNOWN
Platform: UNKNOWN
Classifier: Programming Language :: Python :: 3
Classifier: License :: OSI Approved :: MIT License
Classifier: Operating System :: OS Independent
